cstag/__init__.py
cstag/call.py
cstag/consensus.py
cstag/lengthen.py
cstag/mask.py
cstag/revcomp.py
cstag/shorten.py
cstag/split.py
cstag/to_html.py
cstag/to_sequence.py
cstag/to_vcf.py
cstag/utils/validator.py
cstag-1.1.0.dist-info/LICENSE
cstag-1.1.0.dist-info/METADATA
cstag-1.1.0.dist-info/WHEEL
cstag-1.1.0.dist-info/RECORD
