Metadata-Version: 2.1
Name: cstag
Version: 1.1.0
Summary: Python library tailored for for manipulating and visualizing minimap2's cs tags
Home-page: https://github.com/akikuno/cstag
License: MIT
Author: Akihiro Kuno
Author-email: akuno@md.tsukuba.ac.jp
Requires-Python: >=3.8,<4.0
Classifier: Intended Audience :: Science/Research
Classifier: License :: OSI Approved :: MIT License
Classifier: Operating System :: OS Independent
Classifier: Programming Language :: Python :: 3
Classifier: Programming Language :: Python :: 3.8
Classifier: Programming Language :: Python :: 3.9
Classifier: Programming Language :: Python :: 3.10
Classifier: Programming Language :: Python :: 3.11
Classifier: Programming Language :: Python :: 3.12
Classifier: Topic :: Scientific/Engineering :: Bio-Informatics
Project-URL: Documentation, https://akikuno.github.io/cstag/cstag
Project-URL: Repository, https://github.com/akikuno/cstag
